tensor_schema/__init__.py
tensor_schema/core.py
tensor_schema-0.1.0.dist-info/LICENSE
tensor_schema-0.1.0.dist-info/METADATA
tensor_schema-0.1.0.dist-info/WHEEL
tensor_schema-0.1.0.dist-info/top_level.txt
tensor_schema-0.1.0.dist-info/RECORD
