Metadata-Version: 2.1
Name: tensor-schema
Version: 0.1.0
Summary: A lightweight shape validation system for multimodal tensors
Home-page: https://github.com/bbeckca/tensor-schema
Author: Benji Beck
Author-email: 
License: UNKNOWN
Platform: UNKNOWN
Classifier: Programming Language :: Python :: 3
Classifier: License :: OSI Approved :: Apache Software License
Classifier: Operating System :: OS Independent
Requires-Python: >=3.8
License-File: LICENSE
Requires-Dist: torch>=1.13
Requires-Dist: typing-extensions>=4.5.0
